<?xml version="1.0" encoding="UTF-8"?><plugIn home="src/plugIns/layer5application/loadGeneratorPlugIn_v0_001/client" id="loadGeneratorClient" layer="5" type="CLIENT">
  <plugInSettings>
    <globalCapabilites>
      <duplex>
        <client>TRUE</client>
        <mix>TRUE</mix>
      </duplex>
      <topology>
        <client>FREE_ROUTE</client>
        <mix>FREE_ROUTE</mix>
      </topology>
    </globalCapabilites>
  </plugInSettings>
  <name>Load Generator (Client) v0.001</name>
  <package>plugIns.layer5application.loadGeneratorPlugIn_v0_001</package>
</plugIn>
